ghtrend/__init__.py
ghtrend/repository.py
ghtrend/trend.py
ghtrend-0.1.1.dist-info/METADATA
ghtrend-0.1.1.dist-info/WHEEL
ghtrend-0.1.1.dist-info/entry_points.txt
ghtrend-0.1.1.dist-info/RECORD
